ttast/__init__.py
ttast/__main__.py
ttast/builtin.py
ttast/exception.py
ttast/pipeline.py
ttast/ttast.py
ttast/types.py
ttast/util.py
ttast-0.3.3.dist-info/LICENSE
ttast-0.3.3.dist-info/METADATA
ttast-0.3.3.dist-info/WHEEL
ttast-0.3.3.dist-info/entry_points.txt
ttast-0.3.3.dist-info/top_level.txt
ttast-0.3.3.dist-info/RECORD
